medvis/__init__.py
medvis/functional.py
medvis/mask.py
medvis/__pycache__/__init__.cpython-37.pyc
medvis/__pycache__/functional.cpython-37.pyc
medvis/__pycache__/mask.cpython-37.pyc
medvis-0.0.1.dist-info/LICENSE.txt
medvis-0.0.1.dist-info/METADATA
medvis-0.0.1.dist-info/WHEEL
medvis-0.0.1.dist-info/top_level.txt
medvis-0.0.1.dist-info/RECORD
