Metadata-Version: 2.1
Name: medvis
Version: 0.0.1
Summary: Some utilities to visualise medical images and masks
Home-page: https://github.com/yngvem/medvis
Author: medvis
Author-email: yngve.m.moe@gmail.com
License: "MIT license",
Keywords: medvis
Platform: UNKNOWN
Classifier: Intended Audience :: Developers
Classifier: License :: OSI Approved :: MIT License
Classifier: Natural Language :: English
Classifier: Programming Language :: Python :: 3.6
Classifier: Programming Language :: Python :: 3.7
